bdbots/__init__.py
bdbots/version.py
bdbots-1.0.0.dist-info/licenses/LICENSE
bdbots-1.0.0.dist-info/METADATA
bdbots-1.0.0.dist-info/WHEEL
bdbots-1.0.0.dist-info/top_level.txt
bdbots-1.0.0.dist-info/RECORD
