Metadata-Version: 2.4
Name: bdbots
Version: 1.0.0
Summary: BDBOTS 🇧🇩 – Your trusted tech partner for Telegram bots, Python solutions, website development, and reliable hosting. Powered by expertise, driven by customer satisfaction. ❤️
Author-email: BDBOTS <contact@bdbots.org>
License-Expression: MIT
Project-URL: Homepage, https://github.com/BDBOTS/bdbots
Requires-Python: >=3.9
License-File: LICENSE
Dynamic: license-file
